rjieba-0.1.13.dist-info/METADATA
rjieba-0.1.13.dist-info/WHEEL
rjieba/__init__.py
rjieba/rjieba.abi3.so
rjieba-0.1.13.dist-info/RECORD
