Metadata-Version: 2.4
Name: rjieba
Version: 0.1.13
Summary: jieba-rs Python binding
Author: messense <messense@icloud.com>
Author-email: messense <messense@icloud.com>
License: MIT
Project-URL: Source Code, https://github.com/messense/rjieba-py
